mesh_gtfsr/__init__.py
mesh_gtfsr/defaults.py
mesh_gtfsr/mesh.py
mesh_gtfsr/lib/__init__.py
mesh_gtfsr/lib/gtfs_realtime_pb2.py
mesh_gtfsr-0.0.11.dist-info/LICENSE
mesh_gtfsr-0.0.11.dist-info/METADATA
mesh_gtfsr-0.0.11.dist-info/WHEEL
mesh_gtfsr-0.0.11.dist-info/top_level.txt
mesh_gtfsr-0.0.11.dist-info/RECORD
